{
	"Port1":70, 
	"Port2":71, 
	"Port1_Octal":"\"\\000\\106\"",
	"Port2_Octal":"\"\\000\\107\"",
	"CPU_Port_Octal": "\"\\000\\375\"",
	"Interface2" :"4/0",
	"Interfaces": [
		{
			"name": "1/0",
			"ifindex": 68,
			"enabled": false,
			"operstatus": "DOWN",
			"adminstatus": "UNKNOWN",
			"hardwareport": "",
			"systemidmac": "11:22:33:44:55:66",
			"systempriority": 1000,
			"macaddress": "0:0:0:0:0:0",
			"portspeed": "SPEED_40GB",
			"negotiatedportspeed": "SPEED_40GB",
			"configautonegotiate": false,
			"stateautonegotiate": false,
			"configforwardingviable": true,
			"stateforwardingviable": true,
			"confighealthindicator": "GOOD",
			"statehealthindicator": "GOOD",
			"inbroadcastpkts": 0,
			"indiscards": 0,
			"inerrors": 0,
			"infcserrors": 0,
			"inmulticastpkts": 0,
			"inoctets": 0,
			"inunicastpkts": 0,
			"inunknownprotos": 0,
			"outbroadcastpkts": 0,
			"outdiscards": 0,
			"outerrors": 0,
			"outmulticastpkts": 0,
			"outoctets": 0,
			"outunicastpkts": 0
		},
		{
			"name": "2/0",
			"ifindex": 69,
			"enabled": false,
			"operstatus": "DOWN",
			"adminstatus": "UNKNOWN",
			"hardwareport": "",
			"systemidmac": "11:22:33:44:55:66",
			"systempriority": 1000,
			"macaddress": "0:0:0:0:0:0",
			"portspeed": "SPEED_40GB",
			"negotiatedportspeed": "SPEED_40GB",
			"configautonegotiate": false,
			"stateautonegotiate": false,
			"configforwardingviable": true,
			"stateforwardingviable": true,
			"confighealthindicator": "GOOD",
			"statehealthindicator": "GOOD",
			"inbroadcastpkts": 0,
			"indiscards": 0,
			"inerrors": 0,
			"infcserrors": 0,
			"inmulticastpkts": 0,
			"inoctets": 0,
			"inunicastpkts": 0,
			"inunknownprotos": 0,
			"outbroadcastpkts": 0,
			"outdiscards": 0,
			"outerrors": 0,
			"outmulticastpkts": 0,
			"outoctets": 0,
			"outunicastpkts": 0
		},
		{
			"name": "3/0",
			"ifindex": 70,
			"enabled": true,
			"operstatus": "UP",
			"adminstatus": "UP",
			"hardwareport": "",
			"systemidmac": "11:22:33:44:55:66",
			"systempriority": 1000,
			"macaddress": "0:0:0:0:0:0",
			"portspeed": "SPEED_40GB",
			"negotiatedportspeed": "SPEED_40GB",
			"configautonegotiate": false,
			"stateautonegotiate": false,
			"configforwardingviable": true,
			"stateforwardingviable": true,
			"confighealthindicator": "GOOD",
			"statehealthindicator": "GOOD",
			"inbroadcastpkts": 0,
			"indiscards": 0,
			"inerrors": 0,
			"infcserrors": 0,
			"inmulticastpkts": 0,
			"inoctets": 0,
			"inunicastpkts": 0,
			"inunknownprotos": 0,
			"outbroadcastpkts": 0,
			"outdiscards": 0,
			"outerrors": 0,
			"outmulticastpkts": 0,
			"outoctets": 0,
			"outunicastpkts": 0
		},
		{
			"name": "4/0",
			"ifindex": 71,
			"enabled": true,
			"operstatus": "UP",
			"adminstatus": "UP",
			"hardwareport": "",
			"systemidmac": "11:22:33:44:55:66",
			"systempriority": 1000,
			"macaddress": "0:0:0:0:0:0",
			"portspeed": "SPEED_40GB",
			"negotiatedportspeed": "SPEED_40GB",
			"configautonegotiate": false,
			"stateautonegotiate": false,
			"configforwardingviable": true,
			"stateforwardingviable": true,
			"confighealthindicator": "GOOD",
			"statehealthindicator": "GOOD",
			"inbroadcastpkts": 0,
			"indiscards": 0,
			"inerrors": 0,
			"infcserrors": 0,
			"inmulticastpkts": 0,
			"inoctets": 0,
			"inunicastpkts": 0,
			"inunknownprotos": 0,
			"outbroadcastpkts": 0,
			"outdiscards": 0,
			"outerrors": 0,
			"outmulticastpkts": 0,
			"outoctets": 0,
			"outunicastpkts": 0
		},
		{
			"name": "5/0",
			"ifindex": 37,
			"enabled": false,
			"operstatus": "DOWN",
			"adminstatus": "UNKNOWN",
			"hardwareport": "",
			"systemidmac": "11:22:33:44:55:66",
			"systempriority": 1000,
			"macaddress": "0:0:0:0:0:0",
			"portspeed": "SPEED_40GB",
			"negotiatedportspeed": "SPEED_40GB",
			"configautonegotiate": false,
			"stateautonegotiate": false,
			"configforwardingviable": true,
			"stateforwardingviable": true,
			"confighealthindicator": "GOOD",
			"statehealthindicator": "GOOD",
			"inbroadcastpkts": 0,
			"indiscards": 0,
			"inerrors": 0,
			"infcserrors": 0,
			"inmulticastpkts": 0,
			"inoctets": 0,
			"inunicastpkts": 0,
			"inunknownprotos": 0,
			"outbroadcastpkts": 0,
			"outdiscards": 0,
			"outerrors": 0,
			"outmulticastpkts": 0,
			"outoctets": 0,
			"outunicastpkts": 0
		},
		{
			"name": "6/0",
			"ifindex": 36,
			"enabled": false,
			"operstatus": "DOWN",
			"adminstatus": "UNKNOWN",
			"hardwareport": "",
			"systemidmac": "11:22:33:44:55:66",
			"systempriority": 1000,
			"macaddress": "0:0:0:0:0:0",
			"portspeed": "SPEED_40GB",
			"negotiatedportspeed": "SPEED_40GB",
			"configautonegotiate": false,
			"stateautonegotiate": false,
			"configforwardingviable": true,
			"stateforwardingviable": true,
			"confighealthindicator": "GOOD",
			"statehealthindicator": "GOOD",
			"inbroadcastpkts": 0,
			"indiscards": 0,
			"inerrors": 0,
			"infcserrors": 0,
			"inmulticastpkts": 0,
			"inoctets": 0,
			"inunicastpkts": 0,
			"inunknownprotos": 0,
			"outbroadcastpkts": 0,
			"outdiscards": 0,
			"outerrors": 0,
			"outmulticastpkts": 0,
			"outoctets": 0,
			"outunicastpkts": 0
		}
	]
}
